{
  "id": "422",
  "title": "Adjustable Wrenches",
  "slug": "adjustable-wrenches",
  "description": "Adjustable Wrenches n HSN CODE : 82041220 n TUV Rheinland Certified :ISO 9001:2015 n BSI Certified :ISO 50001:2018 n n n n n n n n n n Adjustable Wrenchen n n Adjustable Wrenche (Insulated)n n n Adjustable Wrenche (Chrome Plated)n n n Adjustable Wrench (Chrome Plated Insulated)n",
  "images": [
    "/images/2022/11/1110.png",
    "/images/2022/11/1110-300x88.png",
    "/images/2022/11/1112.png",
    "/images/2022/11/1112-300x77.png",
    "/images/2022/11/1112-768x197.png",
    "/images/2023/01/1112-chrome-.jpg",
    "/images/2023/01/1112-chrome--300x85.jpg",
    "/images/2023/01/1112-chrome--1024x289.jpg",
    "/images/2023/01/1112-chrome--768x217.jpg",
    "/images/2022/11/1106-CI.png",
    "/images/2022/11/1106-CI-300x77.png",
    "/images/2022/11/1106-CI-768x196.png"
  ]
}