{
  "id": "306",
  "title": "All Products",
  "slug": "all-products",
  "description": "n All Products n n n Lorem ipsum dolor sit amet, consectetur adipiscing elit. Ut elit tellus, luctus nec ullamcorper mattis, pulvinar dapibus leo. n n Lorem ipsum dolor sit amet, consectetur adipiscing elit. Ut elit tellus, luctus nec ullamcorper mattis, pulvinar dapibus leo. n n Lorem ipsum dolor sit amet, consectetur adipiscing elit. Ut elit tellus, luctus nec ullamcorper mattis, pulvinar dapibus leo. n n Lorem ipsum dolor sit amet, consectetur adipiscing elit. Ut elit tellus, luctus nec ullamcorper mattis, pulvinar dapibus leo. n n Lorem ipsum dolor sit amet, consectetur adipiscing elit. Ut elit tellus, luctus nec ullamcorper mattis, pulvinar dapibus leo. n n Lorem ipsum dolor sit amet, consectetur adipiscing elit. Ut elit tellus, luctus nec ullamcorper mattis, pulvinar dapibus leo. n n Lorem ipsum dolor sit amet, consectetur adipiscing elit. Ut elit tellus, luctus nec ullamcorper mattis, pulvinar dapibus leo. n n Lorem ipsum dolor sit amet, consectetur adipiscing elit. Ut elit tellus, luctus nec ullamcorper mattis, pulvinar dapibus leo. n n Lorem ipsum dolor sit amet, consectetur adipiscing elit. Ut elit tellus, luctus nec ullamcorper mattis, pulvinar dapibus leo. n n Lorem ipsum dolor sit amet, consectetur adipiscing elit. Ut elit tellus, luctus nec ullamcorper mattis, pulvinar dapibus leo. n n Lorem ipsum dolor sit amet, consectetur adipiscing elit. Ut elit tellus, luctus nec ullamcorper mattis, pulvinar dapibus leo. n n Lorem ipsum dolor sit amet, consectetur adipiscing elit. Ut elit tellus, luctus nec ullamcorper mattis, pulvinar dapibus leo.",
  "images": [
    "/images/2022/11/Corel-932.png",
    "/images/2022/11/Corel-932-300x98.png",
    "/images/2022/11/Corel-931.png",
    "/images/2022/11/Corel-931-300x103.png",
    "/images/2022/11/Corel-929.png",
    "/images/2022/11/Corel-929-300x62.png",
    "/images/2022/11/Corel-913.png",
    "/images/2022/11/Corel-913-300x78.png",
    "/images/2022/11/Corel-910.png",
    "/images/2022/11/Corel-910-300x92.png",
    "/images/2022/11/Corel-926.png",
    "/images/2022/11/Corel-926-300x147.png",
    "/images/2022/11/Corel-925.png",
    "/images/2022/11/Corel-925-300x167.png",
    "/images/2022/11/Corel-909.png",
    "/images/2022/11/Corel-909-300x120.png",
    "/images/2022/11/Corel-908.png",
    "/images/2022/11/Corel-908-300x92.png",
    "/images/2022/11/Corel-908-ISI.png",
    "/images/2022/11/Corel-908-ISI-300x69.png",
    "/images/2022/11/Corel-908-FI.png",
    "/images/2022/11/Corel-908-FI-300x84.png",
    "/images/2022/11/1112.png",
    "/images/2022/11/1112-300x77.png",
    "/images/2022/11/1112-768x197.png"
  ]
}