{
  "id": "1408",
  "title": "Round Nose Plier",
  "slug": "round-nose-plier",
  "category": "pliers",
  "hsnCode": "",
  "description": "PYE Round Nose Plier (With Thick Insulation) Product No. Length (mm) Standard Packing in Box Standard Packing in Carton PYE 932 155 5 Pcs. 100 Pcs. Reference Standard IS : 3568 - 1990 Backn",
  "images": [
    "/images/2022/11/Corel-932.png",
    "/images/2022/11/Corel-932-300x98.png",
    "/images/2022/11/loader.gif",
    "/images/2022/11/aniso.jpg",
    "/images/2022/11/aniso-300x56.jpg"
  ],
  "rawContent": "<h3>PYE Round Nose Plier</h3>\t\t\t\tn\t\t\t\t\t<h5>(With Thick Insulation)</h5>\t\t\t\tn\t\t\t\t\t\t\t\t\t\t\t\t\t\t\t\t<a href=\"http://localhost/pye/circlip-plier-internal/\">n\t\t\t\t\t\t\t<img width=\"560\" height=\"182\" src=\"https://ludhcloud.com/pye/wp-content/uploads/2022/11/Corel-932.png\" alt=\"\" srcset=\"https://ludhcloud.com/pye/wp-content/uploads/2022/11/Corel-932.png 560w, https://ludhcloud.com/pye/wp-content/uploads/2022/11/Corel-932-300x98.png 300w\" sizes=\"(max-width: 560px) 100vw, 560px\" />\t\t\t\t\t\t\t\t</a>n\t\t<h5 style=\"color: white;\">Product No.</h5><h5 style=\"color: white;\">Length (mm)</h5><h5 style=\"color: white;\">Standard Packing in Box</h5><h5 style=\"color: white;\">Standard Packing in Carton</h5><p>PYE 932</p><p>155</p><p>5 Pcs.</p>\t\tn\t\t\t\t\t\t\t\t\t\t\t\t\t\t\t<img width=\"1920\" height=\"1920\" src=\"https://ludhcloud.com/pye/wp-content/uploads/2022/11/loader.gif\" alt=\"\" />\t\t\t\t\t\t\t\t\t\t\t\t\t\t\tn\t\t<p>100 Pcs.</p>\t\tn\t\t\t\t\t\t\t\t\t\t\t\t\t\t\t<img width=\"1920\" height=\"1920\" src=\"https://ludhcloud.com/pye/wp-content/uploads/2022/11/loader.gif\" alt=\"\" />\t\t\t\t\t\t\t\t\t\t\t\t\t\t\tn\t\t<center>n<h5>Reference Standard IS : 3568 - 1990</h5>\t\tn\t\t\t\t\t\t\t\t\t\t\t\t\t\t\t<img width=\"472\" height=\"88\" src=\"https://ludhcloud.com/pye/wp-content/uploads/2022/11/aniso.jpg\" alt=\"\" srcset=\"https://ludhcloud.com/pye/wp-content/uploads/2022/11/aniso.jpg 472w, https://ludhcloud.com/pye/wp-content/uploads/2022/11/aniso-300x56.jpg 300w\" sizes=\"(max-width: 472px) 100vw, 472px\" />\t\t\t\t\t\t\t\t\t\t\t\t\t\t\tn\t\t\t\t\t<a href=\"http://localhost/pye/pliers/\">n\t\t\t\t\t\t\t\t\tBackn\t\t\t\t\t</a>"
}