{
  "id": "2508",
  "title": "S-400",
  "slug": "s-400",
  "category": "tool-kits",
  "hsnCode": "",
  "description": "PYE Tool Kit - 4 Pcs. n (Heavy Duty Plastic Box) n n n Product No. Description Standard Packing in Box Standard Packing in Carton PYE - S400 Combination Plier 180 mm (907) Screw Driver Two-in-one (576) Measuring Tape - 3 Meter (MT-01) Scrissor Small (SR-01) 1 Pcs. n n 20 Pcs. n n n n Backn",
  "images": [
    "/images/2023/11/s-400.png",
    "/images/2023/11/s-400-300x279.png",
    "/images/2023/11/s-400-768x715.png",
    "/images/2022/11/loader.gif",
    "/images/2022/11/aniso.jpg",
    "/images/2022/11/aniso-300x56.jpg"
  ],
  "rawContent": "<h3>PYE Tool Kit - 4 Pcs.</h3>\t\t\t\tn\t\t\t\t\t<h5>(Heavy Duty Plastic Box)</h5>\t\t\t\tn\t\t\t\t\t\t\t\t\t\t\t\t\t\t\t\t<a href=\"https://ludhcloud.com/pye/s-400/\">n\t\t\t\t\t\t\t<img width=\"862\" height=\"803\" src=\"https://ludhcloud.com/pye/wp-content/uploads/2023/11/s-400.png\" alt=\"\" srcset=\"https://ludhcloud.com/pye/wp-content/uploads/2023/11/s-400.png 862w, https://ludhcloud.com/pye/wp-content/uploads/2023/11/s-400-300x279.png 300w, https://ludhcloud.com/pye/wp-content/uploads/2023/11/s-400-768x715.png 768w\" sizes=\"(max-width: 862px) 100vw, 862px\" />\t\t\t\t\t\t\t\t</a>n\t\t<h5 style=\"color: white;\">Product No.</h5><h5 style=\"color: white;\">Description</h5><h5 style=\"color: white;\">Standard Packing in Box</h5><h5 style=\"color: white;\">Standard Packing in Carton</h5><p>PYE - S400</p><p>Combination Plier 180 mm (907)</p><p>Screw Driver Two-in-one (576)</p><p>Measuring Tape - 3 Meter (MT-01)</p><p>Scrissor Small (SR-01)</p><p>1 Pcs.</p>\t\tn\t\t\t\t\t\t\t\t\t\t\t\t\t\t\t<img width=\"1920\" height=\"1920\" src=\"https://ludhcloud.com/pye/wp-content/uploads/2022/11/loader.gif\" alt=\"\" />\t\t\t\t\t\t\t\t\t\t\t\t\t\t\tn\t\t<p>20 Pcs.</p>\t\tn\t\t\t\t\t\t\t\t\t\t\t\t\t\t\t<img width=\"1920\" height=\"1920\" src=\"https://ludhcloud.com/pye/wp-content/uploads/2022/11/loader.gif\" alt=\"\" />\t\t\t\t\t\t\t\t\t\t\t\t\t\t\tn\t\t\t\t\t\t\t\t\t\t\t\t\t\t\t<img width=\"472\" height=\"88\" src=\"https://ludhcloud.com/pye/wp-content/uploads/2022/11/aniso.jpg\" alt=\"\" srcset=\"https://ludhcloud.com/pye/wp-content/uploads/2022/11/aniso.jpg 472w, https://ludhcloud.com/pye/wp-content/uploads/2022/11/aniso-300x56.jpg 300w\" sizes=\"(max-width: 472px) 100vw, 472px\" />\t\t\t\t\t\t\t\t\t\t\t\t\t\t\tn\t\t\t\t\t<a href=\"http://localhost/pye/pliers/\">n\t\t\t\t\t\t\t\t\tBackn\t\t\t\t\t</a>"
}